ai_tech_crawler/__init__.py
ai_tech_crawler/custom_json_parser.py
ai_tech_crawler/llm_friendly_loader.py
ai_tech_crawler/prompt_factory.py
ai_tech_crawler/smart_scraper.py
ai_tech_crawler/utils.py
ai_tech_crawler-0.0.4.dist-info/licenses/LICENSE
ai_tech_crawler-0.0.4.dist-info/METADATA
ai_tech_crawler-0.0.4.dist-info/WHEEL
ai_tech_crawler-0.0.4.dist-info/top_level.txt
ai_tech_crawler-0.0.4.dist-info/RECORD
