Metadata-Version: 2.4
Name: ai-tech-crawler
Version: 0.0.4
Summary: Autonomous Scraping Agent: Scrape URLs with prompts and schema
Author-email: Rohan Dhanraj Yadav <rohan.dhanraj@aitechsolutionsltd.com>, AI Tech Solutions <aitalents.technology@aitechsolutionsltd.com>
License:                                  Apache License
Project-URL: Homepage, https://github.com/AI-TECH-SOLUTIONS-LTD/smart-scraping-agent
Project-URL: Issues, https://github.com/AI-TECH-SOLUTIONS-LTD/smart-scraping-agent/issues
Classifier: Programming Language :: Python :: 3
Classifier: Operating System :: OS Independent
Requires-Python: >=3.12
License-File: LICENSE
Requires-Dist: fastapi
Requires-Dist: langchain
Requires-Dist: langchain-community
Requires-Dist: langchain-core
Requires-Dist: langchain-openai
Requires-Dist: langchain-text-splitters
Requires-Dist: markdownify
Requires-Dist: playwright
Requires-Dist: python-dotenv
Dynamic: license-file
